darkcode_server/__init__.py
darkcode_server/cli.py
darkcode_server/config.py
darkcode_server/daemon.py
darkcode_server/prompt_ui.py
darkcode_server/qrcode.py
darkcode_server/security.py
darkcode_server/server.py
darkcode_server/tui.py
darkcode_server/web_admin.py
darkcode_server/assets/banner.txt
darkcode_server-0.1.54.dist-info/licenses/LICENSE
darkcode_server-0.1.54.dist-info/METADATA
darkcode_server-0.1.54.dist-info/WHEEL
darkcode_server-0.1.54.dist-info/entry_points.txt
darkcode_server-0.1.54.dist-info/top_level.txt
darkcode_server-0.1.54.dist-info/RECORD
