Metadata-Version: 2.4
Name: darkcode-server
Version: 0.1.54
Summary: Server for DarkCode Agent - Remote Claude Code from your phone
Author: 0xdeadbeef
License: MIT
Project-URL: Homepage, https://github.com/haKC-ai/darkcode-server
Project-URL: Repository, https://github.com/haKC-ai/darkcode-server
Project-URL: Issues, https://github.com/haKC-ai/darkcode-server/issues
Keywords: claude,ai,remote,mobile,websocket
Classifier: Development Status :: 4 - Beta
Classifier: Environment :: Console
Classifier: Intended Audience :: Developers
Classifier: License :: OSI Approved :: MIT License
Classifier: Operating System :: OS Independent
Classifier: Programming Language :: Python :: 3
Classifier: Programming Language :: Python :: 3.9
Classifier: Programming Language :: Python :: 3.10
Classifier: Programming Language :: Python :: 3.11
Classifier: Programming Language :: Python :: 3.12
Classifier: Topic :: Software Development :: Libraries :: Python Modules
Requires-Python: >=3.9
License-File: LICENSE
Requires-Dist: rich>=13.0.0
Requires-Dist: click>=8.0.0
Requires-Dist: websockets>=12.0
Requires-Dist: qrcode>=7.4
Requires-Dist: pydantic>=2.0.0
Requires-Dist: pydantic-settings>=2.0.0
Requires-Dist: cryptography>=41.0.0
Requires-Dist: python-dotenv>=1.0.0
Requires-Dist: prompt_toolkit>=3.0.0
Provides-Extra: dev
Requires-Dist: pytest>=7.0.0; extra == "dev"
Requires-Dist: black>=23.0.0; extra == "dev"
Requires-Dist: ruff>=0.1.0; extra == "dev"
Dynamic: license-file
